{
    "number": 18,
    "year": 2021,
    "days": [
        {
            "date": "2021-05-03",
            "dishes": [
                {
                    "name": "Bio-Pasta mit Bio-Soja-Bolognese (dazu Hartkäse)",
                    "price": "N/A",
                    "ingredients": [
                        "So",
                        "Kn",
                        "Gl",
                        "GlW",
                        "Mi"
                    ]
                },
                {
                    "name": "Asiatische Reispfanne mit Zuckererbsenschoten und Ei",
                    "price": "N/A",
                    "ingredients": [
                        "Ei"
                    ]
                },
                {
                    "name": "Bulgur mit Karotten, Fenchel und Sellerie",
                    "price": "N/A",
                    "ingredients": [
                        "Sl",
                        "Kn",
                        "Gl",
                        "GlW"
                    ]
                },
                {
                    "name": "Tagessuppe",
                    "price": "N/A",
                    "ingredients": []
                },
                {
                    "name": "Spinatspätzlepfanne mit Bergkäse und abgeschmelzten Zwiebeln",
                    "price": "N/A",
                    "ingredients": [
                        "Gl",
                        "Ei",
                        "GlW",
                        "Mi"
                    ]
                },
                {
                    "name": "Alm Cordon bleu gefüllt mit Bergkäse und rohem Schinken",
                    "price": "N/A",
                    "ingredients": [
                        "GlG",
                        "S",
                        "Kn",
                        "Gl",
                        "GlW",
                        "Mi",
                        "Ei",
                        "2"
                    ]
                }
            ]
        },
        {
            "date": "2021-05-04",
            "dishes": [
                {
                    "name": "Bio-Pasta Napoli (Bio-Tomaten-Basilikumsauce)",
                    "price": "N/A",
                    "ingredients": [
                        "Kn",
                        "Gl",
                        "GlW"
                    ]
                },
                {
                    "name": "Pizza Salami",
                    "price": "N/A",
                    "ingredients": [
                        "GlG",
                        "S",
                        "1",
                        "So",
                        "Kn",
                        "Gl",
                        "GlW",
                        "Mi",
                        "2",
                        "3"
                    ]
                },
                {
                    "name": "Gebratenes Rindersteak mit Schrobenhausener Spargel (g.g.A.) und Sauce Hollandaise",
                    "price": "N/A",
                    "ingredients": [
                        "Mi",
                        "Ei",
                        "Sl"
                    ]
                },
                {
                    "name": "Grüne Bohnen-Kartoffel-Gemüse in Kokos-Zitronensauce",
                    "price": "N/A",
                    "ingredients": [
                        "Sf",
                        "Kn",
                        "Gl",
                        "GlW"
                    ]
                },
                {
                    "name": "Tagessuppe",
                    "price": "N/A",
                    "ingredients": []
                },
                {
                    "name": "Überbackenes Rösti mit Spargel (g.g.A.), Tomate und Käse",
                    "price": "N/A",
                    "ingredients": [
                        "Mi",
                        "1",
                        "2"
                    ]
                }
            ]
        },
        {
            "date": "2021-05-05",
            "dishes": [
                {
                    "name": "Pasta mit Champignonrahmsauce",
                    "price": "N/A",
                    "ingredients": [
                        "Kn",
                        "Gl",
                        "GlW",
                        "Mi"
                    ]
                },
                {
                    "name": "Rotes Gemüsecurry",
                    "price": "N/A",
                    "ingredients": [
                        "Kn"
                    ]
                },
                {
                    "name": "Mexikanisches Soja-Chili",
                    "price": "N/A",
                    "ingredients": [
                        "Kn",
                        "So"
                    ]
                },
                {
                    "name": "Limonensuppe mit grünem Spargel",
                    "price": "N/A",
                    "ingredients": [
                        "Mi",
                        "Gl",
                        "GlW"
                    ]
                },
                {
                    "name": "Maultaschen mit Frischkäsefüllung und Spargelragout (g.g.A.)",
                    "price": "N/A",
                    "ingredients": [
                        "Sw",
                        "Sl",
                        "99",
                        "Gl",
                        "GlW",
                        "Mi",
                        "5",
                        "Ei"
                    ]
                },
                {
                    "name": "Zanderfilet mit Sauce Hollandaise",
                    "price": "N/A",
                    "ingredients": [
                        "Sl",
                        "Gl",
                        "GlW",
                        "Fi",
                        "Mi",
                        "Ei"
                    ]
                }
            ]
        },
        {
            "date": "2021-05-06",
            "dishes": [
                {
                    "name": "Bio-Penne mit Bio-Tomaten-Zucchinisauce (dazu Hartkäse)",
                    "price": "N/A",
                    "ingredients": [
                        "Kn",
                        "Gl",
                        "GlW",
                        "Mi"
                    ]
                },
                {
                    "name": "Pizza Mexiko mit Vorderschinken, Mais, Paprikawürfeln und Mozzarella",
                    "price": "N/A",
                    "ingredients": [
                        "GlG",
                        "So",
                        "Gl",
                        "GlW",
                        "8",
                        "Mi",
                        "2",
                        "3"
                    ]
                },
                {
                    "name": "Gegrillter Spargel (g.g.A.) mit Mango-Mandel-Salsa",
                    "price": "N/A",
                    "ingredients": [
                        "ScM",
                        "Sc"
                    ]
                },
                {
                    "name": "Green Thai Curry mit Spargel (g.g.A.) und Rinderstreifen",
                    "price": "N/A",
                    "ingredients": [
                        "So",
                        "Kn",
                        "Gl",
                        "GlW",
                        "R",
                        "2"
                    ]
                },
                {
                    "name": "Bunte Gemüsepaella",
                    "price": "N/A",
                    "ingredients": [
                        "Kn"
                    ]
                },
                {
                    "name": "Tagessuppe",
                    "price": "N/A",
                    "ingredients": []
                }
            ]
        },
        {
            "date": "2021-05-07",
            "dishes": [
                {
                    "name": "Vegane Strozzapreti Carbonara mit Räuchertofu",
                    "price": "N/A",
                    "ingredients": [
                        "Sl",
                        "So",
                        "Kn",
                        "Gl",
                        "GlW"
                    ]
                },
                {
                    "name": "Kartoffeleintopf mit Majoran",
                    "price": "N/A",
                    "ingredients": [
                        "Sl"
                    ]
                },
                {
                    "name": "Tagessuppe",
                    "price": "N/A",
                    "ingredients": []
                },
                {
                    "name": "Halbes Hendl mit Bratensauce",
                    "price": "N/A",
                    "ingredients": [
                        "Sl",
                        "GlG",
                        "Kn",
                        "Gl",
                        "GlW",
                        "Mi"
                    ]
                },
                {
                    "name": "Spargel (g.g.A.) Finkenwerder Art mit Speck und Shrimps",
                    "price": "N/A",
                    "ingredients": [
                        "S",
                        "Kr",
                        "1",
                        "Gl",
                        "GlW",
                        "8",
                        "2",
                        "3"
                    ]
                },
                {
                    "name": "Apfelstrudel mit Vanillesauce",
                    "price": "N/A",
                    "ingredients": [
                        "Gl",
                        "Ei",
                        "GlW",
                        "Mi"
                    ]
                }
            ]
        }
    ]
}