{
    "number": 28,
    "year": 2019,
    "days": [
        {
            "date": "2019-07-08",
            "dishes": [
                {
                    "name": "Bulgur mit Karotten, Fenchel und Sellerie",
                    "price": 1,
                    "ingredients": [
                        "GlW",
                        "Kn",
                        "Sl",
                        "Gl"
                    ]
                },
                {
                    "name": "Pasta mit Sojabolognese",
                    "price": 1.9,
                    "ingredients": [
                        "GlW",
                        "So",
                        "Sl",
                        "Gl"
                    ]
                },
                {
                    "name": "Esterhazygulasch vom Rind (GQB)",
                    "price": 2.8,
                    "ingredients": [
                        "R",
                        "GlG",
                        "Mi",
                        "GlW",
                        "Kn",
                        "Sl",
                        "Gl"
                    ]
                },
                {
                    "name": "Alm Cordon bleu gefüllt mit Bergkäse und rohem Schinken",
                    "price": 4,
                    "ingredients": [
                        "GlG",
                        "S",
                        "Mi",
                        "Ei",
                        "GlW",
                        "Kn",
                        "Gl",
                        "2"
                    ]
                }
            ]
        },
        {
            "date": "2019-07-09",
            "dishes": [
                {
                    "name": "Grüne Bohnen mit Reis in Kokos-Zitronensauce",
                    "price": 1,
                    "ingredients": [
                        "GlW",
                        "Kn",
                        "Gl",
                        "Sf"
                    ]
                },
                {
                    "name": "Kartoffeltaschen mit Kräuterfrischkäse",
                    "price": 2.4,
                    "ingredients": [
                        "GlW",
                        "Kn",
                        "Gl",
                        "Mi"
                    ]
                },
                {
                    "name": "Bratwurstschnecke auf Sauerkraut",
                    "price": 2.6,
                    "ingredients": [
                        "Sl",
                        "8",
                        "S"
                    ]
                },
                {
                    "name": "Kalbsrahmgulasch mit Champignons und Weißwein",
                    "price": 3.0,
                    "ingredients": [
                        "Sw",
                        "Mi",
                        "GlW",
                        "Gl",
                        "99"
                    ]
                },
                {
                    "name": "Burrito-Beef-Bowl (Reis, Chili-Hack, Mais, Salat, Tomate, Guacamole, Sauerrahm und Koriander)",
                    "price": 3.5,
                    "ingredients": [
                        "1",
                        "R",
                        "Mi",
                        "Ei",
                        "Kn",
                        "2",
                        "Sf"
                    ]
                }
            ]
        },
        {
            "date": "2019-07-10",
            "dishes": [
                {
                    "name": "Mexikanisches Chili",
                    "price": 1,
                    "ingredients": [
                        "Kn",
                        "So"
                    ]
                },
                {
                    "name": "Pasta mit Champignonrahmsauce",
                    "price": 1.9,
                    "ingredients": [
                        "GlW",
                        "Kn",
                        "Gl",
                        "Mi"
                    ]
                },
                {
                    "name": "Münchner Schnitzel (Senf-Meerrettichkruste)",
                    "price": 2.4,
                    "ingredients": [
                        "GlG",
                        "S",
                        "Sw",
                        "Mi",
                        "GlW",
                        "Kn",
                        "Gl",
                        "Sf",
                        "3"
                    ]
                },
                {
                    "name": "Pizza Speciale mit Salami, Hinterschinken und Champignons",
                    "price": 2.6,
                    "ingredients": [
                        "S",
                        "Mi",
                        "GlW",
                        "Gl",
                        "2",
                        "Sf",
                        "3"
                    ]
                }
            ]
        },
        {
            "date": "2019-07-11",
            "dishes": [
                {
                    "name": "Bunte Gemüsepaella",
                    "price": 1,
                    "ingredients": [
                        "Kn"
                    ]
                },
                {
                    "name": "Senner Rösti mit Tomate und Käse überbacken",
                    "price": 2.4,
                    "ingredients": [
                        "1",
                        "2",
                        "Mi"
                    ]
                },
                {
                    "name": "Pasta mit orientalischer Lammhacksauce",
                    "price": 2.6,
                    "ingredients": [
                        "ScM",
                        "GlW",
                        "Kn",
                        "Sl",
                        "Gl",
                        "Sc"
                    ]
                },
                {
                    "name": "Arista al fiorentina - Schweinebraten toskanische Art",
                    "price": 2.8,
                    "ingredients": [
                        "GlG",
                        "Sw",
                        "Mi",
                        "GlW",
                        "Kn",
                        "Gl",
                        "99"
                    ]
                },
                {
                    "name": "Tandoori-Chicken-Bowl (Hähnchen, Basmatireis, Mangosalat, Rote Beete, Raita)",
                    "price": 4,
                    "ingredients": [
                        "Mi",
                        "Se",
                        "Kn",
                        "4",
                        "2",
                        "Sf",
                        "9"
                    ]
                }
            ]
        },
        {
            "date": "2019-07-12",
            "dishes": [
                {
                    "name": "Kartoffeleintopf mit Majoran",
                    "price": 1,
                    "ingredients": [
                        "Sl"
                    ]
                },
                {
                    "name": "Mediterrane Schupfnudelpfanne mit frischem Gemüse",
                    "price": 1.9,
                    "ingredients": [
                        "Ei",
                        "GlW",
                        "Sl",
                        "Gl",
                        "Kn"
                    ]
                },
                {
                    "name": "Kartoffeleintopf mit ein Paar Wiener",
                    "price": 2.4,
                    "ingredients": [
                        "R",
                        "S",
                        "8",
                        "Sl",
                        "2",
                        "3"
                    ]
                },
                {
                    "name": "Apfelstrudel mit Vanillesauce",
                    "price": 2.4,
                    "ingredients": [
                        "GlW",
                        "Gl",
                        "Mi"
                    ]
                },
                {
                    "name": "Gebackene Calamari-Ringe mit Zitronen-Knoblauch-Dip",
                    "price": 3.5,
                    "ingredients": [
                        "1",
                        "Wt",
                        "Mi",
                        "Ei",
                        "GlW",
                        "Kn",
                        "Gl"
                    ]
                }
            ]
        }
    ]
}