{
    "number": 42,
    "year": 2019,
    "days": [
        {
            "date": "2019-10-14",
            "dishes": [
                {
                    "name": "Penne all'arrabiata",
                    "price": 1.55,
                    "ingredients": [
                        "Kn",
                        "Gl",
                        "GlW",
                        "2"
                    ]
                },
                {
                    "name": "Rindergeschnetzeltes Stroganoff",
                    "price": 3.2,
                    "ingredients": [
                        "Sf",
                        "9",
                        "GlG",
                        "GlW",
                        "Kn",
                        "Mi",
                        "2",
                        "Gl",
                        "R"
                    ]
                }
            ]
        },
        {
            "date": "2019-10-15",
            "dishes": [
                {
                    "name": "Allgäuer Käsespätzle mit Röstzwiebeln",
                    "price": 2.4,
                    "ingredients": [
                        "GlW",
                        "Ei",
                        "Mi",
                        "1",
                        "GlD",
                        "2",
                        "Gl"
                    ]
                }
            ]
        },
        {
            "date": "2019-10-16",
            "dishes": [
                {
                    "name": "Farfalle mit Tomaten-Frischkäse-Sauce",
                    "price": 1.9,
                    "ingredients": [
                        "Mi",
                        "Gl",
                        "GlW",
                        "Kn"
                    ]
                },
                {
                    "name": "Halbe Schweinshaxe mit Biersauce",
                    "price": 3.0,
                    "ingredients": [
                        "GlG",
                        "S",
                        "GlW",
                        "Kn",
                        "Mi",
                        "Gl"
                    ]
                }
            ]
        },
        {
            "date": "2019-10-17",
            "dishes": [
                {
                    "name": "Frische Rahmschwammerl",
                    "price": 1.9,
                    "ingredients": [
                        "Mi",
                        "Gl",
                        "GlW",
                        "Kn"
                    ]
                },
                {
                    "name": "Spenden - Currywurst",
                    "price": 1.9,
                    "ingredients": [
                        "Sf",
                        "11",
                        "S",
                        "R",
                        "8"
                    ]
                }
            ]
        },
        {
            "date": "2019-10-18",
            "dishes": [
                {
                    "name": "Kaiserschmarrn mit Apfelmus",
                    "price": 2.6,
                    "ingredients": [
                        "GlW",
                        "Ei",
                        "3",
                        "Mi",
                        "Gl"
                    ]
                },
                {
                    "name": "Schollenfilet (MSC) paniert mit Remouladensauce",
                    "price": 2.6,
                    "ingredients": [
                        "Sf",
                        "9",
                        "11",
                        "Fi",
                        "GlW",
                        "Ei",
                        "Mi",
                        "1",
                        "2",
                        "Gl"
                    ]
                }
            ]
        }
    ]
}