{
    "number": 16,
    "year": 2019,
    "days": [
        {
            "date": "2019-04-15",
            "dishes": [
                {
                    "name": "Cannelloni mit Ricotta-Spinat-Füllung und Tomatensauce",
                    "price": "N/A",
                    "ingredients": [
                        "Ei",
                        "Mi",
                        "Sl",
                        "Kn",
                        "GlW",
                        "Gl",
                        "1"
                    ]
                },
                {
                    "name": "Chinapfanne mit Putenfleisch",
                    "price": "N/A",
                    "ingredients": [
                        "So",
                        "Kn",
                        "GlW",
                        "Gl",
                        "Sf"
                    ]
                },
                {
                    "name": "Bulgur mit Karotten, Fenchel und Sellerie",
                    "price": "N/A",
                    "ingredients": [
                        "GlW",
                        "Gl",
                        "Kn",
                        "Sl"
                    ]
                },
                {
                    "name": "Kreolische Tomatensuppe",
                    "price": "N/A",
                    "ingredients": [
                        "GlW",
                        "Gl",
                        "Kn",
                        "Sl"
                    ]
                },
                {
                    "name": "Kartoffeltortilla mit Spinat und Tomatensauce",
                    "price": "N/A",
                    "ingredients": [
                        "Ei",
                        "Mi",
                        "Kn",
                        "GlW",
                        "Gl"
                    ]
                },
                {
                    "name": "Paniertes Truthahnschnitzel mit Currydip",
                    "price": "N/A",
                    "ingredients": [
                        "Ei",
                        "Mi",
                        "GlW",
                        "Gl",
                        "Sf",
                        "1"
                    ]
                }
            ]
        },
        {
            "date": "2019-04-16",
            "dishes": [
                {
                    "name": "Dinkelnudeln mit Hackfleisch Mozzarella und Zucchinis",
                    "price": "N/A",
                    "ingredients": [
                        "S",
                        "Mi",
                        "Gl",
                        "GlD",
                        "R"
                    ]
                },
                {
                    "name": "Holzfällersteak vom Schwein",
                    "price": "N/A",
                    "ingredients": [
                        "GlG",
                        "S",
                        "Mi",
                        "Kn",
                        "3",
                        "GlW",
                        "Gl",
                        "2"
                    ]
                },
                {
                    "name": "Chinapfanne mit Putenfleisch",
                    "price": "N/A",
                    "ingredients": []
                },
                {
                    "name": "Veganer Borschtsch mit Kraut, Kartoffeln und Roter Beete",
                    "price": "N/A",
                    "ingredients": [
                        "So",
                        "Kn",
                        "3",
                        "9",
                        "5"
                    ]
                },
                {
                    "name": "Tomatencremesuppe",
                    "price": "N/A",
                    "ingredients": [
                        "GlW",
                        "Gl",
                        "Kn",
                        "Mi"
                    ]
                },
                {
                    "name": "Südfranzösischer Fischtopf mit Meeresfrüchten und Gemüse",
                    "price": "N/A",
                    "ingredients": [
                        "Wt",
                        "Fi",
                        "Kn",
                        "Kr"
                    ]
                }
            ]
        },
        {
            "date": "2019-04-17",
            "dishes": [
                {
                    "name": "Farfalle mit mediterraner Gemüsesauce",
                    "price": "N/A",
                    "ingredients": [
                        "GlW",
                        "Gl"
                    ]
                },
                {
                    "name": "Zarzuela - Spanische Fischpfanne mit Meeresfrüchten, Oliven und Gemüse",
                    "price": "N/A",
                    "ingredients": [
                        "Wt",
                        "3",
                        "GlW",
                        "Fi",
                        "Gl",
                        "Kr",
                        "1"
                    ]
                },
                {
                    "name": "Mexikanisches Chili",
                    "price": "N/A",
                    "ingredients": [
                        "So",
                        "Kn"
                    ]
                },
                {
                    "name": "Kartoffel- Rote Beetesuppe",
                    "price": "N/A",
                    "ingredients": [
                        "So",
                        "Kn",
                        "3",
                        "9",
                        "5"
                    ]
                },
                {
                    "name": "Münchner Schnitzel (Senf-Meerrettichkruste)",
                    "price": "N/A",
                    "ingredients": [
                        "GlG",
                        "S",
                        "Mi",
                        "Sw",
                        "Kn",
                        "3",
                        "GlW",
                        "Gl",
                        "Sf"
                    ]
                },
                {
                    "name": "Südfranzösischer Fischtopf mit Meeresfrüchten und Gemüse",
                    "price": "N/A",
                    "ingredients": [
                        "Wt",
                        "Fi",
                        "Kn",
                        "Kr"
                    ]
                }
            ]
        }
    ]
}