{
    "number": 36,
    "year": 2019,
    "days": [
        {
            "date": "2019-09-02",
            "dishes": [
                {
                    "name": "Pizza Mexiko mit Vorderschinken, Mais, Paprikawürfeln und Mozzarella",
                    "price": 3.5,
                    "ingredients": [
                        "8",
                        "GlG",
                        "Gl",
                        "GlW",
                        "2",
                        "So",
                        "3",
                        "Mi",
                        "1"
                    ]
                },
                {
                    "name": "Gemüsegulasch",
                    "price": "0.33€ / 100g",
                    "ingredients": [
                        "Kn"
                    ]
                },
                {
                    "name": "Penne all'arrabiata",
                    "price": "0.68€ / 100g",
                    "ingredients": [
                        "GlW",
                        "2",
                        "Gl",
                        "Kn"
                    ]
                },
                {
                    "name": "Pasta mit buntem Gemüse",
                    "price": "N/A",
                    "ingredients": [
                        "Gl",
                        "GlW",
                        "2",
                        "Mi",
                        "1"
                    ]
                },
                {
                    "name": "Pasta Carbonara",
                    "price": "0.68€ / 100g",
                    "ingredients": [
                        "Ei",
                        "Kn",
                        "Gl",
                        "S",
                        "GlW",
                        "2",
                        "Sl",
                        "3",
                        "Mi"
                    ]
                },
                {
                    "name": "Täglich frische Salatbar",
                    "price": "0.68€ / 100g",
                    "ingredients": [
                        "Mi",
                        "Fi",
                        "So",
                        "3"
                    ]
                },
                {
                    "name": "Joghurt mit Kirschen",
                    "price": "N/A",
                    "ingredients": [
                        "Mi"
                    ]
                },
                {
                    "name": "Latte Macchiato Creme",
                    "price": "N/A",
                    "ingredients": [
                        "Mi",
                        "So"
                    ]
                },
                {
                    "name": "Saisonale Beilagensalate",
                    "price": "N/A",
                    "ingredients": []
                },
                {
                    "name": "Rindergeschnetzeltes (GQB) Stroganoff zzgl.1.00€",
                    "price": "0.68€ / 100g",
                    "ingredients": [
                        "Kn",
                        "Gl",
                        "Sf",
                        "GlW",
                        "R",
                        "2",
                        "9",
                        "Mi",
                        "GlG"
                    ]
                },
                {
                    "name": "Hackbraten mit pikanter Rahmsauce zzgl. 0,50€",
                    "price": "N/A",
                    "ingredients": [
                        "Ei",
                        "Kn",
                        "Gl",
                        "Sf",
                        "S",
                        "GlW",
                        "R",
                        "So",
                        "Mi",
                        "GlG"
                    ]
                },
                {
                    "name": "Schaschlik zzgl. 1,00€",
                    "price": "N/A",
                    "ingredients": [
                        "11",
                        "Sf",
                        "S"
                    ]
                },
                {
                    "name": "Ratatouille",
                    "price": "0.68€ / 100g",
                    "ingredients": [
                        "Kn"
                    ]
                },
                {
                    "name": "Reis",
                    "price": "N/A",
                    "ingredients": []
                },
                {
                    "name": "Knöpfle",
                    "price": "N/A",
                    "ingredients": [
                        "GlW",
                        "Ei",
                        "GlD",
                        "Gl"
                    ]
                },
                {
                    "name": "Gebratene Hähnchenbruststreifen in scharfem Gemüse zzgl.1.00€",
                    "price": "0.68€ / 100g",
                    "ingredients": [
                        "GlW",
                        "2",
                        "Gl",
                        "Kn"
                    ]
                },
                {
                    "name": "Rindfleischstreifen (GQB) Spicy Ginger mit Bambussprossen zzgl.1.00€",
                    "price": "N/A",
                    "ingredients": [
                        "Kn",
                        "Se",
                        "Gl",
                        "GlW",
                        "R",
                        "2",
                        "So",
                        "Mi",
                        "GlG"
                    ]
                },
                {
                    "name": "Schaschlik mit Countrykartoffeln und frischem Ratatouille",
                    "price": "Baustellenteller (> 2.40€)",
                    "ingredients": [
                        "Kn",
                        "Gl",
                        "Sf",
                        "S",
                        "GlW",
                        "11"
                    ]
                }
            ]
        },
        {
            "date": "2019-09-03",
            "dishes": [
                {
                    "name": "Pizza mit grünem Spargel, Cocktailtomaten und Mozzarella, Pizza Mexiko mit Vorderschinken, Mais, Paprikawürfeln und Mozzarella",
                    "price": 3.5,
                    "ingredients": [
                        "8",
                        "Gl",
                        "GlW",
                        "2",
                        "So",
                        "3",
                        "Mi",
                        "GlG"
                    ]
                },
                {
                    "name": "Indisches Linsencurry",
                    "price": "0.33€ / 100g",
                    "ingredients": [
                        "Kn",
                        "Sl",
                        "Sf"
                    ]
                },
                {
                    "name": "Schupfnudelpfanne mit frischem Gemüse",
                    "price": "N/A",
                    "ingredients": [
                        "Ei",
                        "Gl",
                        "GlW",
                        "2",
                        "Sl",
                        "Mi"
                    ]
                },
                {
                    "name": "Bulgur-Gemüse-Pfanne",
                    "price": "N/A",
                    "ingredients": [
                        "GlW",
                        "Gl",
                        "Kn"
                    ]
                },
                {
                    "name": "Roastbeef mit Schmorzwiebeln zzgl.1,50€",
                    "price": "0.68€ / 100g",
                    "ingredients": [
                        "Kn",
                        "Gl",
                        "GlW",
                        "R",
                        "Mi",
                        "GlG"
                    ]
                },
                {
                    "name": "Käsekrainer zzgl.0,50€",
                    "price": "N/A",
                    "ingredients": [
                        "8",
                        "Kn",
                        "Gl",
                        "Sf",
                        "S",
                        "GlW",
                        "R",
                        "2",
                        "3",
                        "Mi",
                        "GlG"
                    ]
                },
                {
                    "name": "Pasta mit Gorgonzolasauce",
                    "price": "0.68€ / 100g",
                    "ingredients": [
                        "GlW",
                        "Mi",
                        "Gl"
                    ]
                },
                {
                    "name": "Täglich frische Salatbar",
                    "price": "0.68€ / 100g",
                    "ingredients": [
                        "Mi",
                        "Fi",
                        "So",
                        "3"
                    ]
                },
                {
                    "name": "Quark mit Mango",
                    "price": "N/A",
                    "ingredients": [
                        "Mi"
                    ]
                },
                {
                    "name": "Schokopudding mit Sahne",
                    "price": "N/A",
                    "ingredients": [
                        "Mi"
                    ]
                },
                {
                    "name": "Saisonale Beilagensalate",
                    "price": "N/A",
                    "ingredients": []
                },
                {
                    "name": "Allgäuer Käsespätzle mit Röstzwiebeln",
                    "price": "0.68€ / 100g",
                    "ingredients": [
                        "Ei",
                        "GlD",
                        "Gl",
                        "GlW",
                        "2",
                        "Mi",
                        "1"
                    ]
                },
                {
                    "name": "Pommes frites",
                    "price": "0.68€ / 100g",
                    "ingredients": []
                },
                {
                    "name": "Frisches Grillgemüse",
                    "price": "N/A",
                    "ingredients": [
                        "Kn"
                    ]
                },
                {
                    "name": "Salzkartoffeln",
                    "price": "N/A",
                    "ingredients": []
                },
                {
                    "name": "Countrykartoffeln",
                    "price": "N/A",
                    "ingredients": [
                        "GlW",
                        "Gl"
                    ]
                },
                {
                    "name": "Pasta in pikantem Rindfleisch-Gemüse-Ragout",
                    "price": "0.68€ / 100g",
                    "ingredients": [
                        "Ei",
                        "Kn",
                        "Gl",
                        "GlW",
                        "Sl",
                        "Mi"
                    ]
                },
                {
                    "name": "Hähnchenknusperfilet mit Kartoffelsalat",
                    "price": "Baustellenteller (> 2.40€)",
                    "ingredients": [
                        "GlW",
                        "Gl"
                    ]
                }
            ]
        },
        {
            "date": "2019-09-04",
            "dishes": [
                {
                    "name": "Pizza mit grünem Spargel, Cocktailtomaten und Mozzarella, Pizza Mexiko mit Vorderschinken, Mais, Paprikawürfeln und Mozzarella",
                    "price": 3.5,
                    "ingredients": [
                        "8",
                        "Gl",
                        "GlW",
                        "2",
                        "So",
                        "3",
                        "Mi",
                        "GlG"
                    ]
                },
                {
                    "name": "Spanischer Gemüseeintopf",
                    "price": "0.33€ / 100g",
                    "ingredients": [
                        "Kn"
                    ]
                },
                {
                    "name": "Bulgur-Gemüse-Pfanne",
                    "price": "N/A",
                    "ingredients": [
                        "GlW",
                        "Gl",
                        "Kn"
                    ]
                },
                {
                    "name": "Spaghetti mit Sauce Bolognese",
                    "price": "0.68€ / 100g",
                    "ingredients": [
                        "Kn",
                        "Gl",
                        "GlW",
                        "R",
                        "Sl"
                    ]
                },
                {
                    "name": "Gebratener Reis mit Meeresfrüchten zzgl.1,00€",
                    "price": "0.68€ / 100g",
                    "ingredients": [
                        "Ei",
                        "Kr",
                        "Kn",
                        "Gl",
                        "GlW",
                        "Wt",
                        "2",
                        "Sl",
                        "So",
                        "En"
                    ]
                },
                {
                    "name": "Pasta in pikantem Rindfleisch-Gemüse-Ragout",
                    "price": "0.68€ / 100g",
                    "ingredients": [
                        "Ei",
                        "Kn",
                        "Gl",
                        "GlW",
                        "Sl",
                        "Mi"
                    ]
                },
                {
                    "name": "Farfalle mit Tomaten-Frischkäse-Sauce",
                    "price": "0.68€ / 100g",
                    "ingredients": [
                        "GlW",
                        "Mi",
                        "Gl",
                        "Kn"
                    ]
                },
                {
                    "name": "Basmatireis",
                    "price": "0.68€ / 100g",
                    "ingredients": []
                },
                {
                    "name": "Countrykartoffeln",
                    "price": "N/A",
                    "ingredients": [
                        "GlW",
                        "Gl"
                    ]
                },
                {
                    "name": "Frisches Paprikagemüse mit Rosmarin und Knoblauch",
                    "price": "N/A",
                    "ingredients": [
                        "Kn"
                    ]
                },
                {
                    "name": "Täglich frische Salatbar",
                    "price": "0.68€ / 100g",
                    "ingredients": [
                        "Mi",
                        "Fi",
                        "So",
                        "3"
                    ]
                },
                {
                    "name": "Mandelcreme",
                    "price": "N/A",
                    "ingredients": [
                        "Sc",
                        "ScM",
                        "So",
                        "Mi",
                        "ScH"
                    ]
                },
                {
                    "name": "Quark mit Mango",
                    "price": "N/A",
                    "ingredients": [
                        "Mi"
                    ]
                },
                {
                    "name": "Schokopudding",
                    "price": "N/A",
                    "ingredients": [
                        "Mi"
                    ]
                },
                {
                    "name": "Saisonale Beilagensalate",
                    "price": "N/A",
                    "ingredients": []
                },
                {
                    "name": "Thailändische Frühlingsrolle mit Sweet-Chilisauce",
                    "price": "0.68€ / 100g",
                    "ingredients": [
                        "Ei",
                        "Kn",
                        "Gl",
                        "GlW",
                        "11",
                        "Sl",
                        "So",
                        "Mi"
                    ]
                },
                {
                    "name": "Allgäuer Käsespätzle mit Röstzwiebeln",
                    "price": "N/A",
                    "ingredients": [
                        "Ei",
                        "GlD",
                        "Gl",
                        "GlW",
                        "2",
                        "Mi",
                        "1"
                    ]
                },
                {
                    "name": "Paniertes Hähnchenschnitzel zzgl.1,00€",
                    "price": "N/A",
                    "ingredients": [
                        "Kn",
                        "Gl",
                        "GlW",
                        "Sl",
                        "Mi",
                        "GlG"
                    ]
                },
                {
                    "name": "Halbe Schweinshaxe mit Biersauce",
                    "price": "Baustellenteller (> 2.40€)",
                    "ingredients": [
                        "Kn",
                        "Gl",
                        "S",
                        "GlW",
                        "99",
                        "Mi",
                        "GlG"
                    ]
                },
                {
                    "name": "Kartoffelknödel",
                    "price": "N/A",
                    "ingredients": [
                        "Sw",
                        "2",
                        "3",
                        "5",
                        "1"
                    ]
                },
                {
                    "name": "Krautsalat",
                    "price": "N/A",
                    "ingredients": [
                        "Sw",
                        "3",
                        "5"
                    ]
                }
            ]
        },
        {
            "date": "2019-09-05",
            "dishes": [
                {
                    "name": "Pizza Verdura mit gebratenem Gemüse und Mozzarella",
                    "price": 3.5,
                    "ingredients": [
                        "Kn",
                        "Gl",
                        "GlW",
                        "So",
                        "Mi",
                        "GlG"
                    ]
                },
                {
                    "name": "Couscous mit mediterranem Gemüse",
                    "price": "0.33€ / 100g",
                    "ingredients": [
                        "GlW",
                        "Gl",
                        "Kn"
                    ]
                },
                {
                    "name": "Currywurst mit Honig-Ingwer-Ketchup zzgl.0,50€",
                    "price": "0.68€ / 100g",
                    "ingredients": [
                        "8",
                        "Sf",
                        "S",
                        "R",
                        "11"
                    ]
                },
                {
                    "name": "Bio-Spaghetti bolognese",
                    "price": "0.68€ / 100g",
                    "ingredients": [
                        "Kn",
                        "Gl",
                        "S",
                        "GlW",
                        "R",
                        "Mi"
                    ]
                },
                {
                    "name": "Gemüsemaultaschen mit Kräutersauce",
                    "price": "0.68€ / 100g",
                    "ingredients": [
                        "Ei",
                        "Kn",
                        "Gl",
                        "GlW",
                        "Sl",
                        "Mi"
                    ]
                },
                {
                    "name": "Täglich frische Salatbar",
                    "price": "0.68€ / 100g",
                    "ingredients": [
                        "Mi",
                        "Fi",
                        "So",
                        "3"
                    ]
                },
                {
                    "name": "Joghurt mit Himbeeren",
                    "price": "N/A",
                    "ingredients": [
                        "Mi"
                    ]
                },
                {
                    "name": "Mandelcreme",
                    "price": "N/A",
                    "ingredients": [
                        "Mi",
                        "So",
                        "Sc",
                        "ScH"
                    ]
                },
                {
                    "name": "Saisonale Beilagensalate",
                    "price": "N/A",
                    "ingredients": []
                },
                {
                    "name": "Djuvecreis",
                    "price": "0.68€ / 100g",
                    "ingredients": [
                        "Kn"
                    ]
                },
                {
                    "name": "Süßkartoffel Pommes frites",
                    "price": "N/A",
                    "ingredients": [
                        "1"
                    ]
                },
                {
                    "name": "Leipziger Allerlei, natur",
                    "price": "N/A",
                    "ingredients": []
                },
                {
                    "name": "Semmelknödel",
                    "price": "N/A",
                    "ingredients": [
                        "Ei",
                        "Gl",
                        "GlW",
                        "Mi",
                        "1"
                    ]
                },
                {
                    "name": "Frische Rahmschwammerl",
                    "price": "0.68€ / 100g",
                    "ingredients": [
                        "GlW",
                        "Mi",
                        "Gl",
                        "Kn"
                    ]
                },
                {
                    "name": "Hähnchenstreifen Spicy Ginger mit Bambussprossen zzgl.0,50€",
                    "price": "N/A",
                    "ingredients": [
                        "Kn",
                        "Gl",
                        "GlW",
                        "2",
                        "So",
                        "Mi",
                        "GlG",
                        "En"
                    ]
                },
                {
                    "name": "Halbe Schweinshaxe mit Biersauce zzgl.0,50€",
                    "price": "N/A",
                    "ingredients": [
                        "Kn",
                        "Gl",
                        "S",
                        "GlW",
                        "99",
                        "Mi",
                        "GlG"
                    ]
                },
                {
                    "name": "Cevapcici von der Pute mit Djuvecreis und Ajvar",
                    "price": "Baustellenteller (> 2.40€)",
                    "ingredients": [
                        "Ei",
                        "Kn",
                        "Gl",
                        "Sf",
                        "GlW",
                        "Mi"
                    ]
                }
            ]
        },
        {
            "date": "2019-09-06",
            "dishes": [
                {
                    "name": "Pizza Regina mit (Vorder-)Schinken und Champignons",
                    "price": 3.5,
                    "ingredients": [
                        "8",
                        "GlG",
                        "Gl",
                        "S",
                        "GlW",
                        "2",
                        "So",
                        "3",
                        "Mi",
                        "1"
                    ]
                },
                {
                    "name": "Bauerneintopf",
                    "price": "0.33€ / 100g",
                    "ingredients": [
                        "GlW",
                        "Sl",
                        "Gl"
                    ]
                },
                {
                    "name": "Gebratene Chinanudeln mit Wokgemüse und Ei",
                    "price": "0.68€ / 100g",
                    "ingredients": [
                        "Ei",
                        "Se",
                        "Gl",
                        "Sf",
                        "GlW",
                        "2",
                        "So"
                    ]
                },
                {
                    "name": "Tortellini mit Ricotta-Spinat-Füllung in Kräutersauce",
                    "price": "0.68€ / 100g",
                    "ingredients": [
                        "GlW",
                        "Mi",
                        "Gl",
                        "Kn"
                    ]
                },
                {
                    "name": "Schinkennudeln (Vorderschinken) mit Ei",
                    "price": "0.68€ / 100g",
                    "ingredients": [
                        "Ei",
                        "8",
                        "Kn",
                        "Gl",
                        "S",
                        "GlW",
                        "2",
                        "3",
                        "Mi"
                    ]
                },
                {
                    "name": "Täglich frische Salatbar",
                    "price": "0.68€ / 100g",
                    "ingredients": [
                        "Mi",
                        "Fi",
                        "So",
                        "3"
                    ]
                },
                {
                    "name": "Joghurt mit Kirschen und gerösteten Mandeln",
                    "price": "N/A",
                    "ingredients": [
                        "Mi",
                        "Sc",
                        "ScM"
                    ]
                },
                {
                    "name": "Bayerisch Creme",
                    "price": "N/A",
                    "ingredients": [
                        "Sc",
                        "14",
                        "ScM",
                        "So",
                        "99",
                        "Mi"
                    ]
                },
                {
                    "name": "Saisonale Beilagensalate",
                    "price": "N/A",
                    "ingredients": []
                },
                {
                    "name": "Fischstäbchen (MSC) mit Remouladensauce zzgl.1.00€",
                    "price": "0.68€ / 100g",
                    "ingredients": [
                        "Ei",
                        "Gl",
                        "Sf",
                        "GlW",
                        "Fi",
                        "2",
                        "9",
                        "Mi",
                        "1"
                    ]
                },
                {
                    "name": "Röstkartoffeln",
                    "price": "0.68€ / 100g",
                    "ingredients": []
                },
                {
                    "name": "Petersilien-Wurzelkartoffelgemüse",
                    "price": "N/A",
                    "ingredients": []
                },
                {
                    "name": "Reis-Wildreis-Pilaw",
                    "price": "N/A",
                    "ingredients": []
                },
                {
                    "name": "Schweinesteak mit Gorgonzola überbacken",
                    "price": "Baustellenteller (> 2.40€)",
                    "ingredients": [
                        "GlW",
                        "Mi",
                        "Gl"
                    ]
                },
                {
                    "name": "Röstkartoffeln (2)",
                    "price": "N/A",
                    "ingredients": []
                }
            ]
        }
    ]
}