{
    "number": 51,
    "year": 2019,
    "days": [
        {
            "date": "2019-12-16",
            "dishes": [
                {
                    "name": "Spinatspätzlepfanne mit Bergkäse und abgeschmelzten Zwiebeln",
                    "price": 2.6,
                    "ingredients": [
                        "Ei",
                        "Mi",
                        "Gl",
                        "GlW"
                    ]
                },
                {
                    "name": "Schweinerahmgeschnetzeltes mit Pfifferlingen und Steinpilzen",
                    "price": 3.2,
                    "ingredients": [
                        "GlW",
                        "S",
                        "Kn",
                        "99",
                        "5",
                        "GlG",
                        "Mi",
                        "Gl",
                        "Sw"
                    ]
                }
            ]
        },
        {
            "date": "2019-12-17",
            "dishes": [
                {
                    "name": "Schinkennudeln (Vorderschinken) mit Zwiebeln und Ei",
                    "price": 1.9,
                    "ingredients": [
                        "3",
                        "GlW",
                        "S",
                        "Kn",
                        "Ei",
                        "2",
                        "8",
                        "Mi",
                        "Gl"
                    ]
                },
                {
                    "name": "Kartoffel-Pilz-Auflauf mit frischem Lauch und Dip",
                    "price": 2.4,
                    "ingredients": [
                        "Gl",
                        "Sf",
                        "GlW",
                        "Kn",
                        "Sl",
                        "Ei",
                        "2",
                        "Mi",
                        "1"
                    ]
                }
            ]
        },
        {
            "date": "2019-12-18",
            "dishes": [
                {
                    "name": "Spinatknödel Tiroler Art mit Bergkäse",
                    "price": 2.6,
                    "ingredients": [
                        "Fi",
                        "GlW",
                        "Sl",
                        "Ei",
                        "Mi",
                        "Gl"
                    ]
                },
                {
                    "name": "Boeuf à la mode aus dem Rinderbug",
                    "price": 3.2,
                    "ingredients": [
                        "R",
                        "3",
                        "GlW",
                        "Kn",
                        "99",
                        "5",
                        "Sl",
                        "GlG",
                        "Mi",
                        "Gl",
                        "Sw"
                    ]
                }
            ]
        },
        {
            "date": "2019-12-19",
            "dishes": [
                {
                    "name": "Dinkelnudelpfanne Griechische Art mit Oliven,Schafskäse und Knoblauch",
                    "price": 1.9,
                    "ingredients": [
                        "3",
                        "Kn",
                        "GlD",
                        "6",
                        "Mi",
                        "Gl"
                    ]
                },
                {
                    "name": "Pfannengyros vom Schwein mit Tsatsiki",
                    "price": 3.0,
                    "ingredients": [
                        "3",
                        "S",
                        "Kn",
                        "5",
                        "Mi",
                        "Sw"
                    ]
                }
            ]
        },
        {
            "date": "2019-12-20",
            "dishes": [
                {
                    "name": "Apfelstrudel mit Vanillesauce",
                    "price": 2.4,
                    "ingredients": [
                        "Mi",
                        "Gl",
                        "GlW"
                    ]
                },
                {
                    "name": "Gedünstetes Seelachsfilet (MSC) mit Gemüse und Weißweinsauce",
                    "price": 2.8,
                    "ingredients": [
                        "Fi",
                        "GlW",
                        "Kn",
                        "99",
                        "5",
                        "Sl",
                        "Mi",
                        "Gl",
                        "Sw"
                    ]
                }
            ]
        }
    ]
}