{
    "number": 47,
    "year": 2020,
    "days": [
        {
            "date": "2020-11-16",
            "dishes": [
                {
                    "name": "Gulasch vom Schwein",
                    "price": 1.9,
                    "ingredients": [
                        "S",
                        "GlW",
                        "Mi",
                        "Gl",
                        "GlG",
                        "Kn"
                    ]
                },
                {
                    "name": "Ravioli mit Pilzfüllung in pikanter Kräutersauce",
                    "price": 2.4,
                    "ingredients": [
                        "Ei",
                        "GlW",
                        "Mi",
                        "Sl",
                        "Gl",
                        "Kn"
                    ]
                }
            ]
        },
        {
            "date": "2020-11-17",
            "dishes": [
                {
                    "name": "Mediterraner Nudel-Gemüse-Auflauf",
                    "price": 2.4,
                    "ingredients": [
                        "GlW",
                        "Ei",
                        "2",
                        "Mi",
                        "Gl",
                        "1"
                    ]
                },
                {
                    "name": "Rinderbraten (GQB) mit Rotweinsauce",
                    "price": 3.2,
                    "ingredients": [
                        "GlW",
                        "Sl",
                        "Mi",
                        "Gl",
                        "Sw",
                        "5",
                        "GlG",
                        "Kn",
                        "99",
                        "R"
                    ]
                }
            ]
        },
        {
            "date": "2020-11-18",
            "dishes": [
                {
                    "name": "Knöpflepfanne mit Gemüse und Pilzen",
                    "price": 1.9,
                    "ingredients": [
                        "Ei",
                        "Sl",
                        "GlW",
                        "Gl",
                        "GlD"
                    ]
                },
                {
                    "name": "Überbackenes Hacksteak griechische Art mit Tsatsiki und Reis",
                    "price": 3.0,
                    "ingredients": [
                        "Ei",
                        "2",
                        "Mi",
                        "Sl",
                        "Sw",
                        "1",
                        "5",
                        "Kn",
                        "R",
                        "Sf",
                        "3"
                    ]
                }
            ]
        },
        {
            "date": "2020-11-19",
            "dishes": [
                {
                    "name": "Currynudeln mit gebratenen Gemüsestreifen",
                    "price": 1.55,
                    "ingredients": [
                        "GlW",
                        "Sl",
                        "Gl",
                        "Sf",
                        "Se"
                    ]
                },
                {
                    "name": "Grünkohl-Hanf-Bällchen mit Schnittlauchdip",
                    "price": 2.6,
                    "ingredients": [
                        "Mi"
                    ]
                },
                {
                    "name": "Surbraten vom Schweinehals mit Rosmarinjus",
                    "price": 2.8,
                    "ingredients": [
                        "S",
                        "GlW",
                        "2",
                        "Mi",
                        "8",
                        "Gl",
                        "GlG",
                        "Kn",
                        "3"
                    ]
                }
            ]
        },
        {
            "date": "2020-11-20",
            "dishes": [
                {
                    "name": "Kürbis-Lasagne mit Bergkäse überbacken",
                    "price": 3.0,
                    "ingredients": [
                        "GlW",
                        "So",
                        "Mi",
                        "Gl",
                        "GlG",
                        "Kn",
                        "3"
                    ]
                },
                {
                    "name": "Lachsfilet auf Blattspinat",
                    "price": 4.0,
                    "ingredients": [
                        "GlW",
                        "Mi",
                        "Gl",
                        "Kn",
                        "Fi"
                    ]
                }
            ]
        }
    ]
}